rsyncwrap/__init__.py
rsyncwrap/helpers.py
rsyncwrap/main.py
rsyncwrap-0.1.1.dist-info/METADATA
rsyncwrap-0.1.1.dist-info/WHEEL
rsyncwrap-0.1.1.dist-info/top_level.txt
rsyncwrap-0.1.1.dist-info/RECORD
