Metadata-Version: 2.1
Name: rsyncwrap
Version: 0.1.1
Summary: A python wrapper of rsync that yields stats updates.
Home-page: https://github.com/dmwyatt/rsyncwrap
Author: Dustin Wyatt
Author-email: dustin.wyatt@gmail.com
License: MIT
Platform: UNKNOWN
Requires-Python: ==3.*,>=3.8.0
Provides-Extra: dev
Requires-Dist: wheel (==0.*,>=0.34.2) ; extra == 'dev'
